flask_restless_datamodel/__init__.py
flask_restless_datamodel/datamodel.py
flask_restless_datamodel/helpers.py
flask_restless_datamodel/patches.py
flask_restless_datamodel/render.py
flask_restless_datamodel-0.3.0.dist-info/AUTHORS
flask_restless_datamodel-0.3.0.dist-info/LICENSE
flask_restless_datamodel-0.3.0.dist-info/METADATA
flask_restless_datamodel-0.3.0.dist-info/WHEEL
flask_restless_datamodel-0.3.0.dist-info/pbr.json
flask_restless_datamodel-0.3.0.dist-info/top_level.txt
flask_restless_datamodel-0.3.0.dist-info/RECORD
