Metadata-Version: 2.1
Name: flask-restless-datamodel
Version: 0.3.0
Summary: Server side code to expose a datamodel for the flask-restless client
Home-page: https://github.com/maarten-dp/flask-restless-datamodel
Author: Maarten De Paepe
Author-email: "maarten.de.paepe@gmail.com"
Classifier: Development Status :: 4 - Beta
Classifier: Operating System :: MacOS :: MacOS X
Classifier: Operating System :: Microsoft :: Windows
Classifier: Operating System :: POSIX
Classifier: License :: OSI Approved :: MIT License
Classifier: Programming Language :: Python
Classifier: Programming Language :: Python :: 3.7
License-File: LICENSE
License-File: AUTHORS
Requires-Dist: cereal-lazer
Requires-Dist: flask-restless ==0.17.0
Requires-Dist: pbr >=3.0
